LICENSE
README.md
setup.py
Loli_wrapper.egg-info/PKG-INFO
Loli_wrapper.egg-info/SOURCES.txt
Loli_wrapper.egg-info/dependency_links.txt
Loli_wrapper.egg-info/top_level.txt
loli/__init__.py
loli/handler.py
loli/loli.py