Metadata-Version: 2.1
Name: Loli-wrapper
Version: 1.0.3
Summary: Simple wrapper for loli api.
Home-page: https://loli-api.ml
Author: MagMigo
License: UNKNOWN
Platform: UNKNOWN
Classifier: Programming Language :: Python :: 3.10
Classifier: License :: OSI Approved :: MIT License
Classifier: Operating System :: OS Independent
Requires-Python: >=3.7
License-File: LICENSE
